flarepy/__init__.py
flarepy/algorithm.py
flarepy/arith.py
flarepy/array.py
flarepy/base.py
flarepy/bcast.py
flarepy/blas.py
flarepy/build_info
flarepy/cuda.py
flarepy/data.py
flarepy/device.py
flarepy/features.py
flarepy/graphics.py
flarepy/image.py
flarepy/index.py
flarepy/interop.py
flarepy/lapack.py
flarepy/library.py
flarepy/ml.py
flarepy/random.py
flarepy/signal.py
flarepy/sparse.py
flarepy/statistics.py
flarepy/timer.py
flarepy/util.py
flarepy/vision.py
flarepy-0.3.4.dist-info/METADATA
flarepy-0.3.4.dist-info/WHEEL
flarepy-0.3.4.dist-info/top_level.txt
flarepy-0.3.4.dist-info/RECORD
